[{"type": "multiple", "difficulty": "unknown", "category": "General", "question": "Who was the first Tzar of Russia?", "correct_answer": "Ivan the Terrible", "incorrect_answers": ["Nicolai Terravinasonoff", "Boris Godenoff", "Michael Romanoff"]}, {"type": "multiple", "difficulty": "unknown", "category": "General", "question": "Who said So it shall be written, so it shall be done?", "correct_answer": "Yul Brenner in Ten Commandments", "incorrect_answers": ["Peter OToole in Troy", "Yul Brenner in The King and I", "Richard Harris in Gladiator"]}, {"type": "multiple", "difficulty": "unknown", "category": "General", "question": "What cereal was Tiny eating in the horror film House of 1000 Corpses?", "correct_answer": "Agatha Crispies", "incorrect_answers": ["Coco Pops", "Rice Crispies", "Frosties"]}, {"type": "multiple", "difficulty": "unknown", "category": "General", "question": "What comedian played Danny Vermin, a character form the comedy Johnny Dangerously?", "correct_answer": "Joe Piscopo", "incorrect_answers": ["George Carlin", "Eddie Murphy", "Lenny Bruce"]}, {"type": "multiple", "difficulty": "unknown", "category": "General", "question": "This is considered the first  American sitcom with a gay character.", "correct_answer": "The Corner Bar", "incorrect_answers": ["The Nancy Walker Show", "Soap", "Barney Miller"]}, {"type": "multiple", "difficulty": "unknown", "category": "General", "question": "Which of these animals has lost the ability to synthesize vitamin C?", "correct_answer": "All of these", "incorrect_answers": ["Guinea pigs", "Most bat species", "All simians"]}, {"type": "multiple", "difficulty": "unknown", "category": "General", "question": "What is the literal meaning of the word carnivore which has a Latin origin?", "correct_answer": "Meat eater", "incorrect_answers": ["Blood drinker", "Animal killer", "Monster"]}, {"type": "multiple", "difficulty": "unknown", "category": "General", "question": "Pioneer 11 was the first spacecraft to study Saturn in this year.", "correct_answer": "1979", "incorrect_answers": ["1976", "1975", "1973"]}, {"type": "multiple", "difficulty": "unknown", "category": "General", "question": "Which actor was not among the nominees for best actor in a supporting role at the 76th Academy Awards?", "correct_answer": "Sean Penn", "incorrect_answers": ["Benicio Del Torro", "Tim Robbins", "Alec Baldwin"]}, {"type": "multiple", "difficulty": "unknown", "category": "General", "question": "Can you recycle food scraps?", "correct_answer": "Yes", "incorrect_answers": ["No"]}, {"type": "multiple", "difficulty": "unknown", "category": "General", "question": "What is Secretary Clearys favorite hobby in the comedy film Wedding Crashers?", "correct_answer": "Sailing", "incorrect_answers": ["Writing", "Yachting", "Drinking"]}, {"type": "multiple", "difficulty": "unknown", "category": "General", "question": "Where was the 1986  movie Pretty in Pink set?", "correct_answer": "Chicago", "incorrect_answers": ["New York", "Hollywood", "Los Angeles"]}]